iconlibrary
