Metadata-Version: 1.1
Name: icon-library
Version: 0.0.1
Summary: Inspect installed icon themes.
Home-page: https://launchpad.net/icon-library
Author: Matthew McGowan
Author-email: matthew.joseph.mcgowan@gmail.com
License: LGPLv3
Keywords: freedesktop,icon,theme
Platform: UNKNOWN
Classifier: Development Status :: 4 - Beta
Classifier: Environment :: Console
Classifier: Intended Audience :: Developers
Classifier: Intended Audience :: End Users/Desktop
Classifier: Intended Audience :: Information Technology
Classifier: Intended Audience :: System Administrators
Classifier: License :: OSI Approved :: GNU General Public License v3 (GPLv3)
Classifier: Natural Language :: English
Classifier: Operating System :: POSIX
Classifier: Operating System :: POSIX :: Linux
Classifier: Programming Language :: Python :: 2
Classifier: Programming Language :: Python :: 2 :: Only
Classifier: Topic :: System
Classifier: Topic :: System :: Systems Administration
Classifier: Topic :: Utilities
